{
  "version": 1,
  "kind": "teacher_script_spec",
  "id": "W3SAT",
  "week": 3,
  "title": "생활 대화와 돌봄 종합 복습",
  "roleplayScene": "교회 행사에 참여한 방문객이 화장실 위치를 묻고, 식사 자리에서 음식을 권하고 칭찬하며, 서로 격려하고 작별 인사를 나눈 뒤 기도해 드리겠다고 말한다.",
  "contextHeader": {
    "lessonGoal": "화장실 묻기, 식사 대화, 격려, 작별, 기도 제안을 한 흐름으로 복습한다.",
    "learnersHaveCovered": "학습자는 3주차 평일 표현과 이번 주 누적 복습을 마친 상태다.",
    "successLooksLike": "학습자가 남성형/여성형 어미를 구분하며 핵심 표현을 짝과 함께 소리 내어 말하고, 따뜻한 선교적 태도로 역할극에 참여하면 성공이다."
  },
  "missionGoal": "화장실 묻기, 식사 대화, 격려, 작별, 기도 제안을 한 흐름으로 복습한다.",
  "ministryGuide": "돕고 칭찬하고 따뜻하게 헤어진 뒤 기도로 돌보겠다고 말하면 생활 대화가 자연스럽게 선교적 돌봄으로 이어진다.",
  "teacherFlow": [
    "교회 행사와 식사 자리 장면 소개",
    "화장실 묻기와 식사 대화 따라 말하기",
    "격려와 작별 표현 연결",
    "기도해 드릴게요 문장 연습",
    "생활 대화에서 돌봄으로 이어지는 역할극",
    "주일 동일 복습 미션 안내"
  ],
  "phrases": [
    {
      "variantId": "11",
      "phraseId": 11,
      "category": "daily",
      "korean": "화장실 어디 있어요?",
      "english": "Where is the restroom?",
      "speech": {
        "male": {
          "thai": "ห้องน้ำอยู่ที่ไหนครับ",
          "romanization": "hông-náam yùu thîi-năi khráp",
          "korean_pronunciation": "헝남 유 티 나이 크랍"
        },
        "female": {
          "thai": "ห้องน้ำอยู่ที่ไหนคะ",
          "romanization": "hông-náam yùu thîi-năi khá",
          "korean_pronunciation": "헝남 유 티 나이 카"
        }
      },
      "audio": {
        "male": {
          "normal": "assets/audio/sentences/S11_male_normal.mp3",
          "slow": "assets/audio/sentences/S11_male_slow.mp3",
          "repeat3": "assets/audio/sentences/S11_male_repeat3.mp3"
        },
        "female": {
          "normal": "assets/audio/sentences/S11_female_normal.mp3",
          "slow": "assets/audio/sentences/S11_female_slow.mp3",
          "repeat3": "assets/audio/sentences/S11_female_repeat3.mp3"
        }
      }
    },
    {
      "variantId": "12",
      "phraseId": 12,
      "category": "daily",
      "korean": "맛있게 드세요",
      "english": "Enjoy your meal.",
      "speech": {
        "male": {
          "thai": "ทานให้อร่อยนะครับ",
          "romanization": "thaan hâi a-ròi ná khráp",
          "korean_pronunciation": "탄하이 아러이 나 크랍"
        },
        "female": {
          "thai": "ทานให้อร่อยนะคะ",
          "romanization": "thaan hâi a-ròi ná khá",
          "korean_pronunciation": "탄하이 아러이 나 카"
        }
      },
      "audio": {
        "male": {
          "normal": "assets/audio/sentences/S12_male_normal.mp3",
          "slow": "assets/audio/sentences/S12_male_slow.mp3",
          "repeat3": "assets/audio/sentences/S12_male_repeat3.mp3"
        },
        "female": {
          "normal": "assets/audio/sentences/S12_female_normal.mp3",
          "slow": "assets/audio/sentences/S12_female_slow.mp3",
          "repeat3": "assets/audio/sentences/S12_female_repeat3.mp3"
        }
      }
    },
    {
      "variantId": "13",
      "phraseId": 13,
      "category": "daily",
      "korean": "정말 맛있어요",
      "english": "It's really delicious.",
      "speech": {
        "male": {
          "thai": "อร่อยมากจริง ๆ ครับ",
          "romanization": "a-ròi mâak jing-jing khráp",
          "korean_pronunciation": "아러이 막 찡찡 크랍"
        },
        "female": {
          "thai": "อร่อยมากจริง ๆ ค่ะ",
          "romanization": "a-ròi mâak jing-jing khâ",
          "korean_pronunciation": "아러이 막 찡찡 카"
        }
      },
      "audio": {
        "male": {
          "normal": "assets/audio/sentences/S13_male_normal.mp3",
          "slow": "assets/audio/sentences/S13_male_slow.mp3",
          "repeat3": "assets/audio/sentences/S13_male_repeat3.mp3"
        },
        "female": {
          "normal": "assets/audio/sentences/S13_female_normal.mp3",
          "slow": "assets/audio/sentences/S13_female_slow.mp3",
          "repeat3": "assets/audio/sentences/S13_female_repeat3.mp3"
        }
      }
    },
    {
      "variantId": "14",
      "phraseId": 14,
      "category": "daily",
      "korean": "참 잘했어요",
      "english": "Very good!",
      "speech": {
        "male": {
          "thai": "เก่งมากครับ",
          "romanization": "gèng mâak khráp",
          "korean_pronunciation": "깽 막 크랍"
        },
        "female": {
          "thai": "เก่งมากค่ะ",
          "romanization": "gèng mâak khâ",
          "korean_pronunciation": "깽 막 카"
        }
      },
      "audio": {
        "male": {
          "normal": "assets/audio/sentences/S14_male_normal.mp3",
          "slow": "assets/audio/sentences/S14_male_slow.mp3",
          "repeat3": "assets/audio/sentences/S14_male_repeat3.mp3"
        },
        "female": {
          "normal": "assets/audio/sentences/S14_female_normal.mp3",
          "slow": "assets/audio/sentences/S14_female_slow.mp3",
          "repeat3": "assets/audio/sentences/S14_female_repeat3.mp3"
        }
      }
    },
    {
      "variantId": "15",
      "phraseId": 15,
      "category": "daily",
      "korean": "잘 가요",
      "english": "Good bye.",
      "speech": {
        "male": {
          "thai": "ลาก่อนครับ",
          "romanization": "laa-gàawn khráp",
          "korean_pronunciation": "라껀 크랍"
        },
        "female": {
          "thai": "ลาก่อนค่ะ",
          "romanization": "laa-gàawn khâ",
          "korean_pronunciation": "라껀 카"
        }
      },
      "audio": {
        "male": {
          "normal": "assets/audio/sentences/S15_male_normal.mp3",
          "slow": "assets/audio/sentences/S15_male_slow.mp3",
          "repeat3": "assets/audio/sentences/S15_male_repeat3.mp3"
        },
        "female": {
          "normal": "assets/audio/sentences/S15_female_normal.mp3",
          "slow": "assets/audio/sentences/S15_female_slow.mp3",
          "repeat3": "assets/audio/sentences/S15_female_repeat3.mp3"
        }
      }
    },
    {
      "variantId": "16",
      "phraseId": 16,
      "category": "daily",
      "korean": "다시 만나요",
      "english": "See you again.",
      "speech": {
        "male": {
          "thai": "แล้วพบกันใหม่ครับ",
          "romanization": "láew phóp-gan mài khráp",
          "korean_pronunciation": "래우 폽깐 마이 크랍"
        },
        "female": {
          "thai": "แล้วพบกันใหม่ค่ะ",
          "romanization": "láew phóp-gan mài khâ",
          "korean_pronunciation": "래우 폽깐 마이 카"
        }
      },
      "audio": {
        "male": {
          "normal": "assets/audio/sentences/S16_male_normal.mp3",
          "slow": "assets/audio/sentences/S16_male_slow.mp3",
          "repeat3": "assets/audio/sentences/S16_male_repeat3.mp3"
        },
        "female": {
          "normal": "assets/audio/sentences/S16_female_normal.mp3",
          "slow": "assets/audio/sentences/S16_female_slow.mp3",
          "repeat3": "assets/audio/sentences/S16_female_repeat3.mp3"
        }
      }
    },
    {
      "variantId": "23",
      "phraseId": 23,
      "category": "mission",
      "korean": "기도해 드릴게요",
      "english": "I will pray for you.",
      "speech": {
        "male": {
          "thai": "ผมจะอธิษฐานให้คุณครับ",
          "romanization": "phŏm jà à-thít-thăan hâi khun khráp",
          "korean_pronunciation": "폼 짜 아팃탄 하이 쿤 크랍"
        },
        "female": {
          "thai": "ฉันจะอธิษฐานให้คุณค่ะ",
          "romanization": "chăn jà à-thít-thăan hâi khun khâ",
          "korean_pronunciation": "찬 짜 아팃탄 하이 쿤 카"
        }
      },
      "audio": {
        "male": {
          "normal": "assets/audio/sentences/S23_male_normal.mp3",
          "slow": "assets/audio/sentences/S23_male_slow.mp3",
          "repeat3": "assets/audio/sentences/S23_male_repeat3.mp3"
        },
        "female": {
          "normal": "assets/audio/sentences/S23_female_normal.mp3",
          "slow": "assets/audio/sentences/S23_female_slow.mp3",
          "repeat3": "assets/audio/sentences/S23_female_repeat3.mp3"
        }
      }
    }
  ],
  "keywords": [
    {
      "id": "W020",
      "variantIds": [
        "11"
      ],
      "korean": "화장실",
      "english": "restroom",
      "thai": "ห้องน้ำ",
      "romanization": "hông-náam",
      "koreanPronunciation": "헝남",
      "tier": "core",
      "days": [
        11,
        15,
        25
      ],
      "audio": {
        "male": {
          "normal": "assets/audio/words/W020_male_normal.mp3",
          "slow": "assets/audio/words/W020_male_slow.mp3"
        },
        "female": {
          "normal": "assets/audio/words/W020_female_normal.mp3",
          "slow": "assets/audio/words/W020_female_slow.mp3"
        }
      }
    },
    {
      "id": "W025",
      "variantIds": [
        "12",
        "13"
      ],
      "korean": "맛있다",
      "english": "delicious",
      "thai": "อร่อย",
      "romanization": "a-ròi",
      "koreanPronunciation": "아러이",
      "tier": "core",
      "days": [
        12,
        15,
        25
      ],
      "audio": {
        "male": {
          "normal": "assets/audio/words/W025_male_normal.mp3",
          "slow": "assets/audio/words/W025_male_slow.mp3"
        },
        "female": {
          "normal": "assets/audio/words/W025_female_normal.mp3",
          "slow": "assets/audio/words/W025_female_slow.mp3"
        }
      }
    },
    {
      "id": "W028",
      "variantIds": [
        "14"
      ],
      "korean": "잘하다/똑똑하다",
      "english": "good/skilled",
      "thai": "เก่ง",
      "romanization": "gèng",
      "koreanPronunciation": "깽",
      "tier": "core",
      "days": [
        13,
        15,
        20,
        25
      ],
      "audio": {
        "male": {
          "normal": "assets/audio/words/W028_male_normal.mp3",
          "slow": "assets/audio/words/W028_male_slow.mp3"
        },
        "female": {
          "normal": "assets/audio/words/W028_female_normal.mp3",
          "slow": "assets/audio/words/W028_female_slow.mp3"
        }
      }
    },
    {
      "id": "W029",
      "variantIds": [
        "15"
      ],
      "korean": "안녕히 가세요",
      "english": "goodbye",
      "thai": "ลาก่อน",
      "romanization": "laa-gàawn",
      "koreanPronunciation": "라껀",
      "tier": "core",
      "days": [
        14,
        15,
        25
      ],
      "audio": {
        "male": {
          "normal": "assets/audio/words/W029_male_normal.mp3",
          "slow": "assets/audio/words/W029_male_slow.mp3"
        },
        "female": {
          "normal": "assets/audio/words/W029_female_normal.mp3",
          "slow": "assets/audio/words/W029_female_slow.mp3"
        }
      }
    },
    {
      "id": "W045",
      "variantIds": [
        "23"
      ],
      "korean": "기도하다",
      "english": "pray",
      "thai": "อธิษฐาน",
      "romanization": "à-thít-thăan",
      "koreanPronunciation": "아팃탄",
      "tier": "core",
      "days": [
        23,
        25
      ],
      "audio": {
        "male": {
          "normal": "assets/audio/words/W045_male_normal.mp3",
          "slow": "assets/audio/words/W045_male_slow.mp3"
        },
        "female": {
          "normal": "assets/audio/words/W045_female_normal.mp3",
          "slow": "assets/audio/words/W045_female_slow.mp3"
        }
      }
    }
  ],
  "imageNotes": {
    "primaryImage": {
      "sceneId": "prayer_support",
      "altTextKo": "상대를 위로하며 기도해 주겠다고 말하는 장면",
      "sourcePlan": [
        {
          "type": "local_preferred",
          "assetPath": "assets/images/scenes/prayer_support.jpg",
          "status": "ready"
        },
        {
          "type": "stock_preferred",
          "queries": [
            "prayer support two people church",
            "gentle prayer with friend church"
          ],
          "status": "search_required"
        },
        {
          "type": "ai_fallback",
          "prompt": {
            "scene": "offering prayer for someone",
            "peopleAndAction": "one person listening with care, another offering prayer support with gentle posture",
            "setting": "quiet church corner",
            "mood": "peaceful, caring, sincere",
            "cameraFraming": "medium shot",
            "lighting": "soft indoor light",
            "avoidList": [
              "crowded worship stage",
              "extreme emotion"
            ]
          },
          "status": "generate_if_needed"
        }
      ]
    },
    "keywordImages": [
      {
        "keywordId": "W020",
        "priority": "preferred",
        "sourcePlan": [
          {
            "type": "local_preferred",
            "assetPath": "assets/images/keywords/W020.jpg",
            "status": "missing"
          },
          {
            "type": "stock_preferred",
            "queries": [
              "restroom realistic photo",
              "화장실 learning image"
            ],
            "status": "search_required"
          },
          {
            "type": "ai_fallback",
            "prompt": {
              "scene": "single concept image for restroom",
              "peopleAndAction": "show the concept clearly and simply",
              "setting": "clean realistic learning image",
              "mood": "warm and easy to recognize",
              "cameraFraming": "close or medium crop",
              "lighting": "bright neutral light",
              "avoidList": [
                "blurry or noisy image",
                "heavy watermark",
                "text embedded in photo",
                "theological symbolism without a real scene",
                "sad or confrontational mood when the lesson goal is greeting, welcome, or blessing"
              ]
            },
            "status": "generate_if_needed"
          }
        ]
      },
      {
        "keywordId": "W025",
        "priority": "preferred",
        "sourcePlan": [
          {
            "type": "local_preferred",
            "assetPath": "assets/images/keywords/W025.jpg",
            "status": "missing"
          },
          {
            "type": "stock_preferred",
            "queries": [
              "delicious realistic photo",
              "맛있다 learning image"
            ],
            "status": "search_required"
          },
          {
            "type": "ai_fallback",
            "prompt": {
              "scene": "single concept image for delicious",
              "peopleAndAction": "show the concept clearly and simply",
              "setting": "clean realistic learning image",
              "mood": "warm and easy to recognize",
              "cameraFraming": "close or medium crop",
              "lighting": "bright neutral light",
              "avoidList": [
                "blurry or noisy image",
                "heavy watermark",
                "text embedded in photo",
                "theological symbolism without a real scene",
                "sad or confrontational mood when the lesson goal is greeting, welcome, or blessing"
              ]
            },
            "status": "generate_if_needed"
          }
        ]
      },
      {
        "keywordId": "W028",
        "priority": "optional",
        "sourcePlan": [
          {
            "type": "local_preferred",
            "assetPath": "assets/images/keywords/W028.jpg",
            "status": "missing"
          },
          {
            "type": "stock_preferred",
            "queries": [
              "good/skilled realistic photo",
              "잘하다/똑똑하다 learning image"
            ],
            "status": "search_required"
          },
          {
            "type": "ai_fallback",
            "prompt": {
              "scene": "single concept image for good/skilled",
              "peopleAndAction": "show the concept clearly and simply",
              "setting": "clean realistic learning image",
              "mood": "warm and easy to recognize",
              "cameraFraming": "close or medium crop",
              "lighting": "bright neutral light",
              "avoidList": [
                "blurry or noisy image",
                "heavy watermark",
                "text embedded in photo",
                "theological symbolism without a real scene",
                "sad or confrontational mood when the lesson goal is greeting, welcome, or blessing"
              ]
            },
            "status": "generate_if_needed"
          }
        ]
      },
      {
        "keywordId": "W029",
        "priority": "preferred",
        "sourcePlan": [
          {
            "type": "local_preferred",
            "assetPath": "assets/images/keywords/W029.jpg",
            "status": "missing"
          },
          {
            "type": "stock_preferred",
            "queries": [
              "goodbye realistic photo",
              "안녕히 가세요 learning image"
            ],
            "status": "search_required"
          },
          {
            "type": "ai_fallback",
            "prompt": {
              "scene": "single concept image for goodbye",
              "peopleAndAction": "show the concept clearly and simply",
              "setting": "clean realistic learning image",
              "mood": "warm and easy to recognize",
              "cameraFraming": "close or medium crop",
              "lighting": "bright neutral light",
              "avoidList": [
                "blurry or noisy image",
                "heavy watermark",
                "text embedded in photo",
                "theological symbolism without a real scene",
                "sad or confrontational mood when the lesson goal is greeting, welcome, or blessing"
              ]
            },
            "status": "generate_if_needed"
          }
        ]
      },
      {
        "keywordId": "W045",
        "priority": "preferred",
        "sourcePlan": [
          {
            "type": "local_preferred",
            "assetPath": "assets/images/keywords/W045.jpg",
            "status": "missing"
          },
          {
            "type": "stock_preferred",
            "queries": [
              "pray realistic photo",
              "기도하다 learning image"
            ],
            "status": "search_required"
          },
          {
            "type": "ai_fallback",
            "prompt": {
              "scene": "single concept image for pray",
              "peopleAndAction": "show the concept clearly and simply",
              "setting": "clean realistic learning image",
              "mood": "warm and easy to recognize",
              "cameraFraming": "close or medium crop",
              "lighting": "bright neutral light",
              "avoidList": [
                "blurry or noisy image",
                "heavy watermark",
                "text embedded in photo",
                "theological symbolism without a real scene",
                "sad or confrontational mood when the lesson goal is greeting, welcome, or blessing"
              ]
            },
            "status": "generate_if_needed"
          }
        ]
      }
    ]
  },
  "scriptSections": [
    "lesson_objective",
    "opening_words",
    "phrase_coaching_notes",
    "male_female_ending_reminder",
    "image_cue_notes",
    "roleplay_instructions",
    "ministry_guide_summary",
    "closing_encouragement"
  ]
}
